gspractice/__init__.py
gspractice/gspractice.py
gspractice/makeclfs.py
gspractice/run.py
gspractice/run_gspractice.py
gspractice/data/KNN.joblib
gspractice/data/LRC.joblib
gspractice/data/RFC.joblib
gspractice/data/SVC.joblib
gspractice/data/TCGA_7181_cluster_annotations.tsv
gspractice/data/TCGA_7181_cluster_colors.tsv
gspractice/data/TCGA_7181_cluster_numbers.tsv
gspractice/data/TCGA_7181_df_mutsig_log10.tsv
gspractice/data/TCGA_7181_knn_n5_dis.joblib
gspractice/data/TCGA_7181_lrc_c1.joblib
gspractice/data/TCGA_7181_rfc_ne100.joblib
gspractice/data/TCGA_7181_svc_c1_g01.joblib
gspractice/data/UMAP_projector.joblib
gspractice/data/cosmic_v2_signatures.tsv
GS_PRACTICE-1.0.0.dist-info/LICENSE
GS_PRACTICE-1.0.0.dist-info/METADATA
GS_PRACTICE-1.0.0.dist-info/WHEEL
GS_PRACTICE-1.0.0.dist-info/entry_points.txt
GS_PRACTICE-1.0.0.dist-info/top_level.txt
GS_PRACTICE-1.0.0.dist-info/RECORD
