Metadata-Version: 2.1
Name: GS-PRACTICE
Version: 1.0.0
Summary: Tumor genomic subtyping using mutational signatures
Home-page: https://github.com/shirotak/GS-PRACTICE
Author: shirotak
Author-email: tshiro@kuhp.kyoto-u.ac.jp
License: UNKNOWN
Project-URL: Bug Tracker, https://github.com/shirotak/GS-PRACTICE/issues
Platform: UNKNOWN
Classifier: Programming Language :: Python :: 3
Classifier: License :: OSI Approved :: MIT License
Classifier: Operating System :: OS Independent
Requires-Python: >=3.7
License-File: LICENSE
